sd_metrics_lib/calculators/__init__.py
sd_metrics_lib/calculators/metrics.py
sd_metrics_lib/calculators/velocity.py
sd_metrics_lib/sources/__init__.py
sd_metrics_lib/sources/abstract_worklog.py
sd_metrics_lib/sources/story_points.py
sd_metrics_lib/sources/tasks.py
sd_metrics_lib/sources/worklog.py
sd_metrics_lib/sources/azure/__init__.py
sd_metrics_lib/sources/azure/query.py
sd_metrics_lib/sources/azure/story_points.py
sd_metrics_lib/sources/azure/tasks.py
sd_metrics_lib/sources/azure/worklog.py
sd_metrics_lib/sources/jira/__init__.py
sd_metrics_lib/sources/jira/query.py
sd_metrics_lib/sources/jira/story_points.py
sd_metrics_lib/sources/jira/tasks.py
sd_metrics_lib/sources/jira/worklog.py
sd_metrics_lib/utils/__init__.py
sd_metrics_lib/utils/attributes.py
sd_metrics_lib/utils/cache.py
sd_metrics_lib/utils/enums.py
sd_metrics_lib/utils/generators.py
sd_metrics_lib/utils/storypoints.py
sd_metrics_lib/utils/time.py
sd_metrics_lib/utils/worktime.py
sd_metrics_lib-7.0.0.dist-info/licenses/LICENSE
sd_metrics_lib-7.0.0.dist-info/METADATA
sd_metrics_lib-7.0.0.dist-info/WHEEL
sd_metrics_lib-7.0.0.dist-info/top_level.txt
sd_metrics_lib-7.0.0.dist-info/RECORD
