Metadata-Version: 2.4
Name: sd-metrics-lib
Version: 7.0.0
Summary: Library to calculate various metrics of software development process
Author-email: Igor Zarvanskyi <iclutcher@gmail.com>
License-Expression: MIT
Project-URL: Homepage, https://github.com/clutcher/sd-metrics-lib
Project-URL: Bug Tracker, https://github.com/clutcher/sd-metrics-lib/issues
Classifier: Programming Language :: Python :: 3
Classifier: Operating System :: OS Independent
Requires-Python: >=3.9
License-File: LICENSE
Requires-Dist: python-dateutil>=2.8
Provides-Extra: jira
Requires-Dist: atlassian-python-api>=4.0.7; extra == "jira"
Provides-Extra: azure
Requires-Dist: azure-devops>=7.1.0b4; extra == "azure"
Requires-Dist: msrest>=0.7; extra == "azure"
Dynamic: license-file
